SimaiParser/__init__.py
SimaiParser/cli.py
SimaiParser/core.py
SimaiParser/note.py
SimaiParser/rebuild.py
SimaiParser/timing.py
SimaiParser/slide_calc/__init__.py
SimaiParser/slide_calc/slide_length.py
SimaiParser/slide_calc/Assets/prefab_lengths.json
SimaiParser/slide_calc/core/__init__.py
SimaiParser/slide_calc/core/note_parser.py
SimaiParser/slide_calc/core/slide_rules.py
pysimaiparser-0.2.3.dist-info/licenses/LICENSE.txt
pysimaiparser-0.2.3.dist-info/METADATA
pysimaiparser-0.2.3.dist-info/WHEEL
pysimaiparser-0.2.3.dist-info/entry_points.txt
pysimaiparser-0.2.3.dist-info/top_level.txt
pysimaiparser-0.2.3.dist-info/RECORD
