Metadata-Version: 2.4
Name: PySimaiParser
Version: 0.2.3
Summary: A Python library and command-line tool to parse Simai chart files into JSON.
Author-email: Choimoe <qwqshq@gmail.com>
License-Expression: MIT
Project-URL: Homepage, https://github.com/Choimoe/PySimaiParser
Project-URL: Bug Tracker, https://github.com/Choimoe/PySimaiParser/issues
Keywords: simai,parser,rhythm game,maidata,chart
Classifier: Development Status :: 4 - Beta
Classifier: Intended Audience :: Developers
Classifier: Programming Language :: Python :: 3
Classifier: Programming Language :: Python :: 3.7
Classifier: Programming Language :: Python :: 3.8
Classifier: Programming Language :: Python :: 3.9
Classifier: Programming Language :: Python :: 3.10
Classifier: Programming Language :: Python :: 3.11
Classifier: Programming Language :: Python :: 3.12
Classifier: Operating System :: OS Independent
Classifier: Topic :: Software Development :: Libraries :: Python Modules
Classifier: Topic :: Games/Entertainment :: Arcade
Classifier: Topic :: Text Processing
Requires-Python: >=3.7
License-File: LICENSE.txt
Provides-Extra: dev
Requires-Dist: pytest; extra == "dev"
Requires-Dist: build; extra == "dev"
Requires-Dist: twine; extra == "dev"
Dynamic: license-file
